LICENSE.txt
MANIFEST.in
README.md
setup.py
data/example/example.ini
data/example/example.j2
data/example/example.json
data/example/example.xml
data/example/example.yaml
jinja_cli/__init__.py
jinja_cli/__main__.py
jinja_cli.egg-info/PKG-INFO
jinja_cli.egg-info/SOURCES.txt
jinja_cli.egg-info/dependency_links.txt
jinja_cli.egg-info/entry_points.txt
jinja_cli.egg-info/requires.txt
jinja_cli.egg-info/top_level.txt