Metadata-Version: 2.1
Name: jinja-cli
Version: 1.1.1
Summary: a command line interface to jinja;
Home-page: https://github.com/cykerway/jinja-cli
Author: Cyker Way
Author-email: cykerway@example.com
License: UNKNOWN
Project-URL: Bug Reports, https://github.com/cykerway/jinja-cli/issues
Project-URL: Source, https://github.com/cykerway/jinja-cli
Keywords: jinja template engine
Platform: UNKNOWN
Classifier: Development Status :: 4 - Beta
Classifier: Intended Audience :: Developers
Classifier: Topic :: Software Development
Classifier: License :: OSI Approved :: GNU General Public License v3 (GPLv3)
Classifier: Programming Language :: Python :: 3.6
Classifier: Programming Language :: Python :: 3.7
